[{"class": "java.lang.Long", "function": "toString", "parameters": []}, {"class": "java.lang.Long", "function": "hashCode", "parameters": []}, {"class": "java.lang.Long", "function": "byteValue", "parameters": []}, {"class": "java.lang.Long", "function": "shortValue", "parameters": []}, {"class": "java.lang.Long", "function": "intValue", "parameters": []}, {"class": "java.lang.Long", "function": "longValue", "parameters": []}, {"class": "java.lang.Long", "function": "floatValue", "parameters": []}, {"class": "java.lang.Long", "function": "doubleValue", "parameters": []}, {"class": "java.lang.Long", "function": "wait", "parameters": []}, {"class": "java.lang.Long", "function": "getClass", "parameters": []}, {"class": "java.lang.Long", "function": "notify", "parameters": []}, {"class": "java.lang.Long", "function": "notifyAll", "parameters": []}]