[{"class": "java.nio.file.attribute.UserPrincipalLookupService", "function": "wait", "parameters": []}, {"class": "java.nio.file.attribute.UserPrincipalLookupService", "function": "toString", "parameters": []}, {"class": "java.nio.file.attribute.UserPrincipalLookupService", "function": "hashCode", "parameters": []}, {"class": "java.nio.file.attribute.UserPrincipalLookupService", "function": "getClass", "parameters": []}, {"class": "java.nio.file.attribute.UserPrincipalLookupService", "function": "notify", "parameters": []}, {"class": "java.nio.file.attribute.UserPrincipalLookupService", "function": "notifyAll", "parameters": []}]