[{"class": "javax.net.ssl.SSLPermission", "function": "newPermissionCollection", "parameters": []}, {"class": "javax.net.ssl.SSLPermission", "function": "hashCode", "parameters": []}, {"class": "javax.net.ssl.SSLPermission", "function": "getActions", "parameters": []}, {"class": "javax.net.ssl.SSLPermission", "function": "toString", "parameters": []}, {"class": "javax.net.ssl.SSLPermission", "function": "getName", "parameters": []}, {"class": "javax.net.ssl.SSLPermission", "function": "wait", "parameters": []}, {"class": "javax.net.ssl.SSLPermission", "function": "getClass", "parameters": []}, {"class": "javax.net.ssl.SSLPermission", "function": "notify", "parameters": []}, {"class": "javax.net.ssl.SSLPermission", "function": "notifyAll", "parameters": []}]