[{"parameters":[],"class":"com.sun.javadoc.RootDoc","function":"specifiedPackages"},{"parameters":[],"class":"com.sun.javadoc.RootDoc","function":"specifiedClasses"},{"parameters":["class java.lang.String"],"class":"com.sun.javadoc.RootDoc","function":"packageNamed"},{"parameters":["class java.lang.String"],"class":"com.sun.javadoc.RootDoc","function":"classNamed"},{"parameters":[],"class":"com.sun.javadoc.RootDoc","function":"classes"},{"parameters":[],"class":"com.sun.javadoc.RootDoc","function":"options"},{"parameters":["class java.lang.String"],"class":"com.sun.javadoc.RootDoc","function":"tags"},{"parameters":[],"class":"com.sun.javadoc.RootDoc","function":"tags"},{"parameters":[],"class":"com.sun.javadoc.RootDoc","function":"isClass"},{"parameters":[],"class":"com.sun.javadoc.RootDoc","function":"isIncluded"},{"parameters":[],"class":"com.sun.javadoc.RootDoc","function":"commentText"},{"parameters":[],"class":"com.sun.javadoc.RootDoc","function":"seeTags"},{"parameters":[],"class":"com.sun.javadoc.RootDoc","function":"inlineTags"},{"parameters":[],"class":"com.sun.javadoc.RootDoc","function":"firstSentenceTags"},{"parameters":[],"class":"com.sun.javadoc.RootDoc","function":"getRawCommentText"},{"parameters":["class java.lang.String"],"class":"com.sun.javadoc.RootDoc","function":"setRawCommentText"},{"parameters":[],"class":"com.sun.javadoc.RootDoc","function":"isAnnotationTypeElement"},{"parameters":[],"class":"com.sun.javadoc.RootDoc","function":"isException"},{"parameters":[],"class":"com.sun.javadoc.RootDoc","function":"isAnnotationType"},{"parameters":[],"class":"com.sun.javadoc.RootDoc","function":"isOrdinaryClass"},{"parameters":[],"class":"com.sun.javadoc.RootDoc","function":"name"},{"parameters":[],"class":"com.sun.javadoc.RootDoc","function":"isInterface"},{"parameters":["class java.lang.Object"],"class":"com.sun.javadoc.RootDoc","function":"compareTo"},{"parameters":[],"class":"com.sun.javadoc.RootDoc","function":"isEnum"},{"parameters":[],"class":"com.sun.javadoc.RootDoc","function":"isMethod"},{"parameters":[],"class":"com.sun.javadoc.RootDoc","function":"isConstructor"},{"parameters":[],"class":"com.sun.javadoc.RootDoc","function":"position"},{"parameters":[],"class":"com.sun.javadoc.RootDoc","function":"isEnumConstant"},{"parameters":[],"class":"com.sun.javadoc.RootDoc","function":"isField"},{"parameters":[],"class":"com.sun.javadoc.RootDoc","function":"isError"},{"parameters":["class java.lang.String"],"class":"com.sun.javadoc.RootDoc","function":"printError"},{"parameters":["interface com.sun.javadoc.SourcePosition","class java.lang.String"],"class":"com.sun.javadoc.RootDoc","function":"printError"},{"parameters":["interface com.sun.javadoc.SourcePosition","class java.lang.String"],"class":"com.sun.javadoc.RootDoc","function":"printWarning"},{"parameters":["class java.lang.String"],"class":"com.sun.javadoc.RootDoc","function":"printWarning"},{"parameters":["class java.lang.String"],"class":"com.sun.javadoc.RootDoc","function":"printNotice"},{"parameters":["interface com.sun.javadoc.SourcePosition","class java.lang.String"],"class":"com.sun.javadoc.RootDoc","function":"printNotice"}]