[{"parameters":[],"class":"com.sun.jdi.PathSearchingVirtualMachine","function":"classPath"},{"parameters":[],"class":"com.sun.jdi.PathSearchingVirtualMachine","function":"bootClassPath"},{"parameters":[],"class":"com.sun.jdi.PathSearchingVirtualMachine","function":"baseDirectory"},{"parameters":[],"class":"com.sun.jdi.PathSearchingVirtualMachine","function":"dispose"},{"parameters":[],"class":"com.sun.jdi.PathSearchingVirtualMachine","function":"description"},{"parameters":[],"class":"com.sun.jdi.PathSearchingVirtualMachine","function":"eventQueue"},{"parameters":["java.util.Map<? extends com.sun.jdi.ReferenceType, byte[]>"],"class":"com.sun.jdi.PathSearchingVirtualMachine","function":"redefineClasses"},{"parameters":[],"class":"com.sun.jdi.PathSearchingVirtualMachine","function":"process"},{"parameters":[],"class":"com.sun.jdi.PathSearchingVirtualMachine","function":"allClasses"},{"parameters":[],"class":"com.sun.jdi.PathSearchingVirtualMachine","function":"allModules"},{"parameters":["class java.lang.String"],"class":"com.sun.jdi.PathSearchingVirtualMachine","function":"classesByName"},{"parameters":[],"class":"com.sun.jdi.PathSearchingVirtualMachine","function":"allThreads"},{"parameters":[],"class":"com.sun.jdi.PathSearchingVirtualMachine","function":"topLevelThreadGroups"},{"parameters":[],"class":"com.sun.jdi.PathSearchingVirtualMachine","function":"eventRequestManager"},{"parameters":["float"],"class":"com.sun.jdi.PathSearchingVirtualMachine","function":"mirrorOf"},{"parameters":["long"],"class":"com.sun.jdi.PathSearchingVirtualMachine","function":"mirrorOf"},{"parameters":["double"],"class":"com.sun.jdi.PathSearchingVirtualMachine","function":"mirrorOf"},{"parameters":["class java.lang.String"],"class":"com.sun.jdi.PathSearchingVirtualMachine","function":"mirrorOf"},{"parameters":["boolean"],"class":"com.sun.jdi.PathSearchingVirtualMachine","function":"mirrorOf"},{"parameters":["byte"],"class":"com.sun.jdi.PathSearchingVirtualMachine","function":"mirrorOf"},{"parameters":["char"],"class":"com.sun.jdi.PathSearchingVirtualMachine","function":"mirrorOf"},{"parameters":["int"],"class":"com.sun.jdi.PathSearchingVirtualMachine","function":"mirrorOf"},{"parameters":["short"],"class":"com.sun.jdi.PathSearchingVirtualMachine","function":"mirrorOf"},{"parameters":[],"class":"com.sun.jdi.PathSearchingVirtualMachine","function":"mirrorOfVoid"},{"parameters":[],"class":"com.sun.jdi.PathSearchingVirtualMachine","function":"canWatchFieldModification"},{"parameters":[],"class":"com.sun.jdi.PathSearchingVirtualMachine","function":"canWatchFieldAccess"},{"parameters":[],"class":"com.sun.jdi.PathSearchingVirtualMachine","function":"canGetBytecodes"},{"parameters":[],"class":"com.sun.jdi.PathSearchingVirtualMachine","function":"canGetSyntheticAttribute"},{"parameters":[],"class":"com.sun.jdi.PathSearchingVirtualMachine","function":"canGetOwnedMonitorInfo"},{"parameters":[],"class":"com.sun.jdi.PathSearchingVirtualMachine","function":"canGetCurrentContendedMonitor"},{"parameters":[],"class":"com.sun.jdi.PathSearchingVirtualMachine","function":"canGetMonitorInfo"},{"parameters":[],"class":"com.sun.jdi.PathSearchingVirtualMachine","function":"canUseInstanceFilters"},{"parameters":[],"class":"com.sun.jdi.PathSearchingVirtualMachine","function":"canRedefineClasses"},{"parameters":[],"class":"com.sun.jdi.PathSearchingVirtualMachine","function":"canAddMethod"},{"parameters":[],"class":"com.sun.jdi.PathSearchingVirtualMachine","function":"canUnrestrictedlyRedefineClasses"},{"parameters":[],"class":"com.sun.jdi.PathSearchingVirtualMachine","function":"canPopFrames"},{"parameters":[],"class":"com.sun.jdi.PathSearchingVirtualMachine","function":"canGetSourceDebugExtension"},{"parameters":[],"class":"com.sun.jdi.PathSearchingVirtualMachine","function":"canRequestVMDeathEvent"},{"parameters":[],"class":"com.sun.jdi.PathSearchingVirtualMachine","function":"canGetMethodReturnValues"},{"parameters":[],"class":"com.sun.jdi.PathSearchingVirtualMachine","function":"canGetInstanceInfo"},{"parameters":[],"class":"com.sun.jdi.PathSearchingVirtualMachine","function":"canUseSourceNameFilters"},{"parameters":[],"class":"com.sun.jdi.PathSearchingVirtualMachine","function":"canForceEarlyReturn"},{"parameters":[],"class":"com.sun.jdi.PathSearchingVirtualMachine","function":"canBeModified"},{"parameters":[],"class":"com.sun.jdi.PathSearchingVirtualMachine","function":"canRequestMonitorEvents"},{"parameters":[],"class":"com.sun.jdi.PathSearchingVirtualMachine","function":"canGetMonitorFrameInfo"},{"parameters":[],"class":"com.sun.jdi.PathSearchingVirtualMachine","function":"canGetClassFileVersion"},{"parameters":[],"class":"com.sun.jdi.PathSearchingVirtualMachine","function":"canGetConstantPool"},{"parameters":[],"class":"com.sun.jdi.PathSearchingVirtualMachine","function":"canGetModuleInfo"},{"parameters":["class java.lang.String"],"class":"com.sun.jdi.PathSearchingVirtualMachine","function":"setDefaultStratum"},{"parameters":[],"class":"com.sun.jdi.PathSearchingVirtualMachine","function":"getDefaultStratum"},{"parameters":["java.util.List<? extends com.sun.jdi.ReferenceType>"],"class":"com.sun.jdi.PathSearchingVirtualMachine","function":"instanceCounts"},{"parameters":["int"],"class":"com.sun.jdi.PathSearchingVirtualMachine","function":"setDebugTraceMode"},{"parameters":[],"class":"com.sun.jdi.PathSearchingVirtualMachine","function":"name"},{"parameters":["int"],"class":"com.sun.jdi.PathSearchingVirtualMachine","function":"exit"},{"parameters":[],"class":"com.sun.jdi.PathSearchingVirtualMachine","function":"version"},{"parameters":[],"class":"com.sun.jdi.PathSearchingVirtualMachine","function":"suspend"},{"parameters":[],"class":"com.sun.jdi.PathSearchingVirtualMachine","function":"resume"},{"parameters":[],"class":"com.sun.jdi.PathSearchingVirtualMachine","function":"virtualMachine"},{"parameters":[],"class":"com.sun.jdi.PathSearchingVirtualMachine","function":"toString"}]