[{"parameters":["class java.lang.String"],"class":"com.sun.jdi.request.ClassUnloadRequest","function":"addClassFilter"},{"parameters":["class java.lang.String"],"class":"com.sun.jdi.request.ClassUnloadRequest","function":"addClassExclusionFilter"},{"parameters":["class java.lang.Object","class java.lang.Object"],"class":"com.sun.jdi.request.ClassUnloadRequest","function":"putProperty"},{"parameters":[],"class":"com.sun.jdi.request.ClassUnloadRequest","function":"isEnabled"},{"parameters":["boolean"],"class":"com.sun.jdi.request.ClassUnloadRequest","function":"setEnabled"},{"parameters":[],"class":"com.sun.jdi.request.ClassUnloadRequest","function":"disable"},{"parameters":[],"class":"com.sun.jdi.request.ClassUnloadRequest","function":"enable"},{"parameters":["int"],"class":"com.sun.jdi.request.ClassUnloadRequest","function":"addCountFilter"},{"parameters":["int"],"class":"com.sun.jdi.request.ClassUnloadRequest","function":"setSuspendPolicy"},{"parameters":[],"class":"com.sun.jdi.request.ClassUnloadRequest","function":"suspendPolicy"},{"parameters":["class java.lang.Object"],"class":"com.sun.jdi.request.ClassUnloadRequest","function":"getProperty"},{"parameters":[],"class":"com.sun.jdi.request.ClassUnloadRequest","function":"virtualMachine"},{"parameters":[],"class":"com.sun.jdi.request.ClassUnloadRequest","function":"toString"}]