[{"parameters":["java.util.Collection<javax.security.auth.x500.X500Principal>"],"class":"java.security.cert.X509CRLSelector","function":"setIssuers"},{"parameters":["java.util.Collection<?>"],"class":"java.security.cert.X509CRLSelector","function":"setIssuerNames"},{"parameters":["class javax.security.auth.x500.X500Principal"],"class":"java.security.cert.X509CRLSelector","function":"addIssuer"},{"parameters":["class [B"],"class":"java.security.cert.X509CRLSelector","function":"addIssuerName"},{"parameters":["class java.lang.String"],"class":"java.security.cert.X509CRLSelector","function":"addIssuerName"},{"parameters":["class java.math.BigInteger"],"class":"java.security.cert.X509CRLSelector","function":"setMinCRLNumber"},{"parameters":["class java.math.BigInteger"],"class":"java.security.cert.X509CRLSelector","function":"setMaxCRLNumber"},{"parameters":["class java.util.Date"],"class":"java.security.cert.X509CRLSelector","function":"setDateAndTime"},{"parameters":["class java.security.cert.X509Certificate"],"class":"java.security.cert.X509CRLSelector","function":"setCertificateChecking"},{"parameters":[],"class":"java.security.cert.X509CRLSelector","function":"getIssuers"},{"parameters":[],"class":"java.security.cert.X509CRLSelector","function":"getIssuerNames"},{"parameters":[],"class":"java.security.cert.X509CRLSelector","function":"getMinCRL"},{"parameters":[],"class":"java.security.cert.X509CRLSelector","function":"getMaxCRL"},{"parameters":[],"class":"java.security.cert.X509CRLSelector","function":"getDateAndTime"},{"parameters":[],"class":"java.security.cert.X509CRLSelector","function":"getCertificateChecking"},{"parameters":[],"class":"java.security.cert.X509CRLSelector","function":"toString"},{"parameters":[],"class":"java.security.cert.X509CRLSelector","function":"clone"},{"parameters":["class java.security.cert.CRL"],"class":"java.security.cert.X509CRLSelector","function":"match"},{"parameters":["long"],"class":"java.security.cert.X509CRLSelector","function":"wait"},{"parameters":["long","int"],"class":"java.security.cert.X509CRLSelector","function":"wait"},{"parameters":[],"class":"java.security.cert.X509CRLSelector","function":"wait"},{"parameters":["class java.lang.Object"],"class":"java.security.cert.X509CRLSelector","function":"equals"},{"parameters":[],"class":"java.security.cert.X509CRLSelector","function":"hashCode"},{"parameters":[],"class":"java.security.cert.X509CRLSelector","function":"getClass"},{"parameters":[],"class":"java.security.cert.X509CRLSelector","function":"notify"},{"parameters":[],"class":"java.security.cert.X509CRLSelector","function":"notifyAll"}]