[{"parameters":["class javax.swing.plaf.synth.SynthContext","class java.awt.Graphics","int","int","int","int"],"class":"javax.swing.plaf.synth.SynthPainter","function":"paintArrowButtonBackground"},{"parameters":["class javax.swing.plaf.synth.SynthContext","class java.awt.Graphics","int","int","int","int"],"class":"javax.swing.plaf.synth.SynthPainter","function":"paintArrowButtonBorder"},{"parameters":["class javax.swing.plaf.synth.SynthContext","class java.awt.Graphics","int","int","int","int","int"],"class":"javax.swing.plaf.synth.SynthPainter","function":"paintArrowButtonForeground"},{"parameters":["class javax.swing.plaf.synth.SynthContext","class java.awt.Graphics","int","int","int","int"],"class":"javax.swing.plaf.synth.SynthPainter","function":"paintButtonBackground"},{"parameters":["class javax.swing.plaf.synth.SynthContext","class java.awt.Graphics","int","int","int","int"],"class":"javax.swing.plaf.synth.SynthPainter","function":"paintButtonBorder"},{"parameters":["class javax.swing.plaf.synth.SynthContext","class java.awt.Graphics","int","int","int","int"],"class":"javax.swing.plaf.synth.SynthPainter","function":"paintCheckBoxMenuItemBackground"},{"parameters":["class javax.swing.plaf.synth.SynthContext","class java.awt.Graphics","int","int","int","int"],"class":"javax.swing.plaf.synth.SynthPainter","function":"paintCheckBoxMenuItemBorder"},{"parameters":["class javax.swing.plaf.synth.SynthContext","class java.awt.Graphics","int","int","int","int"],"class":"javax.swing.plaf.synth.SynthPainter","function":"paintCheckBoxBackground"},{"parameters":["class javax.swing.plaf.synth.SynthContext","class java.awt.Graphics","int","int","int","int"],"class":"javax.swing.plaf.synth.SynthPainter","function":"paintCheckBoxBorder"},{"parameters":["class javax.swing.plaf.synth.SynthContext","class java.awt.Graphics","int","int","int","int"],"class":"javax.swing.plaf.synth.SynthPainter","function":"paintColorChooserBackground"},{"parameters":["class javax.swing.plaf.synth.SynthContext","class java.awt.Graphics","int","int","int","int"],"class":"javax.swing.plaf.synth.SynthPainter","function":"paintColorChooserBorder"},{"parameters":["class javax.swing.plaf.synth.SynthContext","class java.awt.Graphics","int","int","int","int"],"class":"javax.swing.plaf.synth.SynthPainter","function":"paintComboBoxBackground"},{"parameters":["class javax.swing.plaf.synth.SynthContext","class java.awt.Graphics","int","int","int","int"],"class":"javax.swing.plaf.synth.SynthPainter","function":"paintComboBoxBorder"},{"parameters":["class javax.swing.plaf.synth.SynthContext","class java.awt.Graphics","int","int","int","int"],"class":"javax.swing.plaf.synth.SynthPainter","function":"paintDesktopIconBackground"},{"parameters":["class javax.swing.plaf.synth.SynthContext","class java.awt.Graphics","int","int","int","int"],"class":"javax.swing.plaf.synth.SynthPainter","function":"paintDesktopIconBorder"},{"parameters":["class javax.swing.plaf.synth.SynthContext","class java.awt.Graphics","int","int","int","int"],"class":"javax.swing.plaf.synth.SynthPainter","function":"paintDesktopPaneBackground"},{"parameters":["class javax.swing.plaf.synth.SynthContext","class java.awt.Graphics","int","int","int","int"],"class":"javax.swing.plaf.synth.SynthPainter","function":"paintDesktopPaneBorder"},{"parameters":["class javax.swing.plaf.synth.SynthContext","class java.awt.Graphics","int","int","int","int"],"class":"javax.swing.plaf.synth.SynthPainter","function":"paintEditorPaneBackground"},{"parameters":["class javax.swing.plaf.synth.SynthContext","class java.awt.Graphics","int","int","int","int"],"class":"javax.swing.plaf.synth.SynthPainter","function":"paintEditorPaneBorder"},{"parameters":["class javax.swing.plaf.synth.SynthContext","class java.awt.Graphics","int","int","int","int"],"class":"javax.swing.plaf.synth.SynthPainter","function":"paintFileChooserBackground"},{"parameters":["class javax.swing.plaf.synth.SynthContext","class java.awt.Graphics","int","int","int","int"],"class":"javax.swing.plaf.synth.SynthPainter","function":"paintFileChooserBorder"},{"parameters":["class javax.swing.plaf.synth.SynthContext","class java.awt.Graphics","int","int","int","int"],"class":"javax.swing.plaf.synth.SynthPainter","function":"paintFormattedTextFieldBackground"},{"parameters":["class javax.swing.plaf.synth.SynthContext","class java.awt.Graphics","int","int","int","int"],"class":"javax.swing.plaf.synth.SynthPainter","function":"paintFormattedTextFieldBorder"},{"parameters":["class javax.swing.plaf.synth.SynthContext","class java.awt.Graphics","int","int","int","int"],"class":"javax.swing.plaf.synth.SynthPainter","function":"paintInternalFrameTitlePaneBackground"},{"parameters":["class javax.swing.plaf.synth.SynthContext","class java.awt.Graphics","int","int","int","int"],"class":"javax.swing.plaf.synth.SynthPainter","function":"paintInternalFrameTitlePaneBorder"},{"parameters":["class javax.swing.plaf.synth.SynthContext","class java.awt.Graphics","int","int","int","int"],"class":"javax.swing.plaf.synth.SynthPainter","function":"paintInternalFrameBackground"},{"parameters":["class javax.swing.plaf.synth.SynthContext","class java.awt.Graphics","int","int","int","int"],"class":"javax.swing.plaf.synth.SynthPainter","function":"paintInternalFrameBorder"},{"parameters":["class javax.swing.plaf.synth.SynthContext","class java.awt.Graphics","int","int","int","int"],"class":"javax.swing.plaf.synth.SynthPainter","function":"paintLabelBackground"},{"parameters":["class javax.swing.plaf.synth.SynthContext","class java.awt.Graphics","int","int","int","int"],"class":"javax.swing.plaf.synth.SynthPainter","function":"paintLabelBorder"},{"parameters":["class javax.swing.plaf.synth.SynthContext","class java.awt.Graphics","int","int","int","int"],"class":"javax.swing.plaf.synth.SynthPainter","function":"paintListBackground"},{"parameters":["class javax.swing.plaf.synth.SynthContext","class java.awt.Graphics","int","int","int","int"],"class":"javax.swing.plaf.synth.SynthPainter","function":"paintListBorder"},{"parameters":["class javax.swing.plaf.synth.SynthContext","class java.awt.Graphics","int","int","int","int"],"class":"javax.swing.plaf.synth.SynthPainter","function":"paintMenuBarBackground"},{"parameters":["class javax.swing.plaf.synth.SynthContext","class java.awt.Graphics","int","int","int","int"],"class":"javax.swing.plaf.synth.SynthPainter","function":"paintMenuBarBorder"},{"parameters":["class javax.swing.plaf.synth.SynthContext","class java.awt.Graphics","int","int","int","int"],"class":"javax.swing.plaf.synth.SynthPainter","function":"paintMenuItemBackground"},{"parameters":["class javax.swing.plaf.synth.SynthContext","class java.awt.Graphics","int","int","int","int"],"class":"javax.swing.plaf.synth.SynthPainter","function":"paintMenuItemBorder"},{"parameters":["class javax.swing.plaf.synth.SynthContext","class java.awt.Graphics","int","int","int","int"],"class":"javax.swing.plaf.synth.SynthPainter","function":"paintMenuBackground"},{"parameters":["class javax.swing.plaf.synth.SynthContext","class java.awt.Graphics","int","int","int","int"],"class":"javax.swing.plaf.synth.SynthPainter","function":"paintMenuBorder"},{"parameters":["class javax.swing.plaf.synth.SynthContext","class java.awt.Graphics","int","int","int","int"],"class":"javax.swing.plaf.synth.SynthPainter","function":"paintOptionPaneBackground"},{"parameters":["class javax.swing.plaf.synth.SynthContext","class java.awt.Graphics","int","int","int","int"],"class":"javax.swing.plaf.synth.SynthPainter","function":"paintOptionPaneBorder"},{"parameters":["class javax.swing.plaf.synth.SynthContext","class java.awt.Graphics","int","int","int","int"],"class":"javax.swing.plaf.synth.SynthPainter","function":"paintPanelBackground"},{"parameters":["class javax.swing.plaf.synth.SynthContext","class java.awt.Graphics","int","int","int","int"],"class":"javax.swing.plaf.synth.SynthPainter","function":"paintPanelBorder"},{"parameters":["class javax.swing.plaf.synth.SynthContext","class java.awt.Graphics","int","int","int","int"],"class":"javax.swing.plaf.synth.SynthPainter","function":"paintPasswordFieldBackground"},{"parameters":["class javax.swing.plaf.synth.SynthContext","class java.awt.Graphics","int","int","int","int"],"class":"javax.swing.plaf.synth.SynthPainter","function":"paintPasswordFieldBorder"},{"parameters":["class javax.swing.plaf.synth.SynthContext","class java.awt.Graphics","int","int","int","int"],"class":"javax.swing.plaf.synth.SynthPainter","function":"paintPopupMenuBackground"},{"parameters":["class javax.swing.plaf.synth.SynthContext","class java.awt.Graphics","int","int","int","int"],"class":"javax.swing.plaf.synth.SynthPainter","function":"paintPopupMenuBorder"},{"parameters":["class javax.swing.plaf.synth.SynthContext","class java.awt.Graphics","int","int","int","int"],"class":"javax.swing.plaf.synth.SynthPainter","function":"paintProgressBarBackground"},{"parameters":["class javax.swing.plaf.synth.SynthContext","class java.awt.Graphics","int","int","int","int","int"],"class":"javax.swing.plaf.synth.SynthPainter","function":"paintProgressBarBackground"},{"parameters":["class javax.swing.plaf.synth.SynthContext","class java.awt.Graphics","int","int","int","int"],"class":"javax.swing.plaf.synth.SynthPainter","function":"paintProgressBarBorder"},{"parameters":["class javax.swing.plaf.synth.SynthContext","class java.awt.Graphics","int","int","int","int","int"],"class":"javax.swing.plaf.synth.SynthPainter","function":"paintProgressBarBorder"},{"parameters":["class javax.swing.plaf.synth.SynthContext","class java.awt.Graphics","int","int","int","int","int"],"class":"javax.swing.plaf.synth.SynthPainter","function":"paintProgressBarForeground"},{"parameters":["class javax.swing.plaf.synth.SynthContext","class java.awt.Graphics","int","int","int","int"],"class":"javax.swing.plaf.synth.SynthPainter","function":"paintRadioButtonMenuItemBackground"},{"parameters":["class javax.swing.plaf.synth.SynthContext","class java.awt.Graphics","int","int","int","int"],"class":"javax.swing.plaf.synth.SynthPainter","function":"paintRadioButtonMenuItemBorder"},{"parameters":["class javax.swing.plaf.synth.SynthContext","class java.awt.Graphics","int","int","int","int"],"class":"javax.swing.plaf.synth.SynthPainter","function":"paintRadioButtonBackground"},{"parameters":["class javax.swing.plaf.synth.SynthContext","class java.awt.Graphics","int","int","int","int"],"class":"javax.swing.plaf.synth.SynthPainter","function":"paintRadioButtonBorder"},{"parameters":["class javax.swing.plaf.synth.SynthContext","class java.awt.Graphics","int","int","int","int"],"class":"javax.swing.plaf.synth.SynthPainter","function":"paintRootPaneBackground"},{"parameters":["class javax.swing.plaf.synth.SynthContext","class java.awt.Graphics","int","int","int","int"],"class":"javax.swing.plaf.synth.SynthPainter","function":"paintRootPaneBorder"},{"parameters":["class javax.swing.plaf.synth.SynthContext","class java.awt.Graphics","int","int","int","int","int"],"class":"javax.swing.plaf.synth.SynthPainter","function":"paintScrollBarBackground"},{"parameters":["class javax.swing.plaf.synth.SynthContext","class java.awt.Graphics","int","int","int","int"],"class":"javax.swing.plaf.synth.SynthPainter","function":"paintScrollBarBackground"},{"parameters":["class javax.swing.plaf.synth.SynthContext","class java.awt.Graphics","int","int","int","int"],"class":"javax.swing.plaf.synth.SynthPainter","function":"paintScrollBarBorder"},{"parameters":["class javax.swing.plaf.synth.SynthContext","class java.awt.Graphics","int","int","int","int","int"],"class":"javax.swing.plaf.synth.SynthPainter","function":"paintScrollBarBorder"},{"parameters":["class javax.swing.plaf.synth.SynthContext","class java.awt.Graphics","int","int","int","int","int"],"class":"javax.swing.plaf.synth.SynthPainter","function":"paintScrollBarThumbBackground"},{"parameters":["class javax.swing.plaf.synth.SynthContext","class java.awt.Graphics","int","int","int","int","int"],"class":"javax.swing.plaf.synth.SynthPainter","function":"paintScrollBarThumbBorder"},{"parameters":["class javax.swing.plaf.synth.SynthContext","class java.awt.Graphics","int","int","int","int"],"class":"javax.swing.plaf.synth.SynthPainter","function":"paintScrollBarTrackBackground"},{"parameters":["class javax.swing.plaf.synth.SynthContext","class java.awt.Graphics","int","int","int","int","int"],"class":"javax.swing.plaf.synth.SynthPainter","function":"paintScrollBarTrackBackground"},{"parameters":["class javax.swing.plaf.synth.SynthContext","class java.awt.Graphics","int","int","int","int"],"class":"javax.swing.plaf.synth.SynthPainter","function":"paintScrollBarTrackBorder"},{"parameters":["class javax.swing.plaf.synth.SynthContext","class java.awt.Graphics","int","int","int","int","int"],"class":"javax.swing.plaf.synth.SynthPainter","function":"paintScrollBarTrackBorder"},{"parameters":["class javax.swing.plaf.synth.SynthContext","class java.awt.Graphics","int","int","int","int"],"class":"javax.swing.plaf.synth.SynthPainter","function":"paintScrollPaneBackground"},{"parameters":["class javax.swing.plaf.synth.SynthContext","class java.awt.Graphics","int","int","int","int"],"class":"javax.swing.plaf.synth.SynthPainter","function":"paintScrollPaneBorder"},{"parameters":["class javax.swing.plaf.synth.SynthContext","class java.awt.Graphics","int","int","int","int","int"],"class":"javax.swing.plaf.synth.SynthPainter","function":"paintSeparatorBackground"},{"parameters":["class javax.swing.plaf.synth.SynthContext","class java.awt.Graphics","int","int","int","int"],"class":"javax.swing.plaf.synth.SynthPainter","function":"paintSeparatorBackground"},{"parameters":["class javax.swing.plaf.synth.SynthContext","class java.awt.Graphics","int","int","int","int"],"class":"javax.swing.plaf.synth.SynthPainter","function":"paintSeparatorBorder"},{"parameters":["class javax.swing.plaf.synth.SynthContext","class java.awt.Graphics","int","int","int","int","int"],"class":"javax.swing.plaf.synth.SynthPainter","function":"paintSeparatorBorder"},{"parameters":["class javax.swing.plaf.synth.SynthContext","class java.awt.Graphics","int","int","int","int","int"],"class":"javax.swing.plaf.synth.SynthPainter","function":"paintSeparatorForeground"},{"parameters":["class javax.swing.plaf.synth.SynthContext","class java.awt.Graphics","int","int","int","int"],"class":"javax.swing.plaf.synth.SynthPainter","function":"paintSliderBackground"},{"parameters":["class javax.swing.plaf.synth.SynthContext","class java.awt.Graphics","int","int","int","int","int"],"class":"javax.swing.plaf.synth.SynthPainter","function":"paintSliderBackground"},{"parameters":["class javax.swing.plaf.synth.SynthContext","class java.awt.Graphics","int","int","int","int"],"class":"javax.swing.plaf.synth.SynthPainter","function":"paintSliderBorder"},{"parameters":["class javax.swing.plaf.synth.SynthContext","class java.awt.Graphics","int","int","int","int","int"],"class":"javax.swing.plaf.synth.SynthPainter","function":"paintSliderBorder"},{"parameters":["class javax.swing.plaf.synth.SynthContext","class java.awt.Graphics","int","int","int","int","int"],"class":"javax.swing.plaf.synth.SynthPainter","function":"paintSliderThumbBackground"},{"parameters":["class javax.swing.plaf.synth.SynthContext","class java.awt.Graphics","int","int","int","int","int"],"class":"javax.swing.plaf.synth.SynthPainter","function":"paintSliderThumbBorder"},{"parameters":["class javax.swing.plaf.synth.SynthContext","class java.awt.Graphics","int","int","int","int","int"],"class":"javax.swing.plaf.synth.SynthPainter","function":"paintSliderTrackBackground"},{"parameters":["class javax.swing.plaf.synth.SynthContext","class java.awt.Graphics","int","int","int","int"],"class":"javax.swing.plaf.synth.SynthPainter","function":"paintSliderTrackBackground"},{"parameters":["class javax.swing.plaf.synth.SynthContext","class java.awt.Graphics","int","int","int","int"],"class":"javax.swing.plaf.synth.SynthPainter","function":"paintSliderTrackBorder"},{"parameters":["class javax.swing.plaf.synth.SynthContext","class java.awt.Graphics","int","int","int","int","int"],"class":"javax.swing.plaf.synth.SynthPainter","function":"paintSliderTrackBorder"},{"parameters":["class javax.swing.plaf.synth.SynthContext","class java.awt.Graphics","int","int","int","int"],"class":"javax.swing.plaf.synth.SynthPainter","function":"paintSpinnerBackground"},{"parameters":["class javax.swing.plaf.synth.SynthContext","class java.awt.Graphics","int","int","int","int"],"class":"javax.swing.plaf.synth.SynthPainter","function":"paintSpinnerBorder"},{"parameters":["class javax.swing.plaf.synth.SynthContext","class java.awt.Graphics","int","int","int","int","int"],"class":"javax.swing.plaf.synth.SynthPainter","function":"paintSplitPaneDividerBackground"},{"parameters":["class javax.swing.plaf.synth.SynthContext","class java.awt.Graphics","int","int","int","int"],"class":"javax.swing.plaf.synth.SynthPainter","function":"paintSplitPaneDividerBackground"},{"parameters":["class javax.swing.plaf.synth.SynthContext","class java.awt.Graphics","int","int","int","int","int"],"class":"javax.swing.plaf.synth.SynthPainter","function":"paintSplitPaneDividerForeground"},{"parameters":["class javax.swing.plaf.synth.SynthContext","class java.awt.Graphics","int","int","int","int","int"],"class":"javax.swing.plaf.synth.SynthPainter","function":"paintSplitPaneDragDivider"},{"parameters":["class javax.swing.plaf.synth.SynthContext","class java.awt.Graphics","int","int","int","int"],"class":"javax.swing.plaf.synth.SynthPainter","function":"paintSplitPaneBackground"},{"parameters":["class javax.swing.plaf.synth.SynthContext","class java.awt.Graphics","int","int","int","int"],"class":"javax.swing.plaf.synth.SynthPainter","function":"paintSplitPaneBorder"},{"parameters":["class javax.swing.plaf.synth.SynthContext","class java.awt.Graphics","int","int","int","int"],"class":"javax.swing.plaf.synth.SynthPainter","function":"paintTabbedPaneBackground"},{"parameters":["class javax.swing.plaf.synth.SynthContext","class java.awt.Graphics","int","int","int","int"],"class":"javax.swing.plaf.synth.SynthPainter","function":"paintTabbedPaneBorder"},{"parameters":["class javax.swing.plaf.synth.SynthContext","class java.awt.Graphics","int","int","int","int"],"class":"javax.swing.plaf.synth.SynthPainter","function":"paintTabbedPaneTabAreaBackground"},{"parameters":["class javax.swing.plaf.synth.SynthContext","class java.awt.Graphics","int","int","int","int","int"],"class":"javax.swing.plaf.synth.SynthPainter","function":"paintTabbedPaneTabAreaBackground"},{"parameters":["class javax.swing.plaf.synth.SynthContext","class java.awt.Graphics","int","int","int","int"],"class":"javax.swing.plaf.synth.SynthPainter","function":"paintTabbedPaneTabAreaBorder"},{"parameters":["class javax.swing.plaf.synth.SynthContext","class java.awt.Graphics","int","int","int","int","int"],"class":"javax.swing.plaf.synth.SynthPainter","function":"paintTabbedPaneTabAreaBorder"},{"parameters":["class javax.swing.plaf.synth.SynthContext","class java.awt.Graphics","int","int","int","int","int"],"class":"javax.swing.plaf.synth.SynthPainter","function":"paintTabbedPaneTabBackground"},{"parameters":["class javax.swing.plaf.synth.SynthContext","class java.awt.Graphics","int","int","int","int","int","int"],"class":"javax.swing.plaf.synth.SynthPainter","function":"paintTabbedPaneTabBackground"},{"parameters":["class javax.swing.plaf.synth.SynthContext","class java.awt.Graphics","int","int","int","int","int"],"class":"javax.swing.plaf.synth.SynthPainter","function":"paintTabbedPaneTabBorder"},{"parameters":["class javax.swing.plaf.synth.SynthContext","class java.awt.Graphics","int","int","int","int","int","int"],"class":"javax.swing.plaf.synth.SynthPainter","function":"paintTabbedPaneTabBorder"},{"parameters":["class javax.swing.plaf.synth.SynthContext","class java.awt.Graphics","int","int","int","int"],"class":"javax.swing.plaf.synth.SynthPainter","function":"paintTabbedPaneContentBackground"},{"parameters":["class javax.swing.plaf.synth.SynthContext","class java.awt.Graphics","int","int","int","int"],"class":"javax.swing.plaf.synth.SynthPainter","function":"paintTabbedPaneContentBorder"},{"parameters":["class javax.swing.plaf.synth.SynthContext","class java.awt.Graphics","int","int","int","int"],"class":"javax.swing.plaf.synth.SynthPainter","function":"paintTableHeaderBackground"},{"parameters":["class javax.swing.plaf.synth.SynthContext","class java.awt.Graphics","int","int","int","int"],"class":"javax.swing.plaf.synth.SynthPainter","function":"paintTableHeaderBorder"},{"parameters":["class javax.swing.plaf.synth.SynthContext","class java.awt.Graphics","int","int","int","int"],"class":"javax.swing.plaf.synth.SynthPainter","function":"paintTableBackground"},{"parameters":["class javax.swing.plaf.synth.SynthContext","class java.awt.Graphics","int","int","int","int"],"class":"javax.swing.plaf.synth.SynthPainter","function":"paintTableBorder"},{"parameters":["class javax.swing.plaf.synth.SynthContext","class java.awt.Graphics","int","int","int","int"],"class":"javax.swing.plaf.synth.SynthPainter","function":"paintTextAreaBackground"},{"parameters":["class javax.swing.plaf.synth.SynthContext","class java.awt.Graphics","int","int","int","int"],"class":"javax.swing.plaf.synth.SynthPainter","function":"paintTextAreaBorder"},{"parameters":["class javax.swing.plaf.synth.SynthContext","class java.awt.Graphics","int","int","int","int"],"class":"javax.swing.plaf.synth.SynthPainter","function":"paintTextPaneBackground"},{"parameters":["class javax.swing.plaf.synth.SynthContext","class java.awt.Graphics","int","int","int","int"],"class":"javax.swing.plaf.synth.SynthPainter","function":"paintTextPaneBorder"},{"parameters":["class javax.swing.plaf.synth.SynthContext","class java.awt.Graphics","int","int","int","int"],"class":"javax.swing.plaf.synth.SynthPainter","function":"paintTextFieldBackground"},{"parameters":["class javax.swing.plaf.synth.SynthContext","class java.awt.Graphics","int","int","int","int"],"class":"javax.swing.plaf.synth.SynthPainter","function":"paintTextFieldBorder"},{"parameters":["class javax.swing.plaf.synth.SynthContext","class java.awt.Graphics","int","int","int","int"],"class":"javax.swing.plaf.synth.SynthPainter","function":"paintToggleButtonBackground"},{"parameters":["class javax.swing.plaf.synth.SynthContext","class java.awt.Graphics","int","int","int","int"],"class":"javax.swing.plaf.synth.SynthPainter","function":"paintToggleButtonBorder"},{"parameters":["class javax.swing.plaf.synth.SynthContext","class java.awt.Graphics","int","int","int","int"],"class":"javax.swing.plaf.synth.SynthPainter","function":"paintToolBarBackground"},{"parameters":["class javax.swing.plaf.synth.SynthContext","class java.awt.Graphics","int","int","int","int","int"],"class":"javax.swing.plaf.synth.SynthPainter","function":"paintToolBarBackground"},{"parameters":["class javax.swing.plaf.synth.SynthContext","class java.awt.Graphics","int","int","int","int","int"],"class":"javax.swing.plaf.synth.SynthPainter","function":"paintToolBarBorder"},{"parameters":["class javax.swing.plaf.synth.SynthContext","class java.awt.Graphics","int","int","int","int"],"class":"javax.swing.plaf.synth.SynthPainter","function":"paintToolBarBorder"},{"parameters":["class javax.swing.plaf.synth.SynthContext","class java.awt.Graphics","int","int","int","int"],"class":"javax.swing.plaf.synth.SynthPainter","function":"paintToolBarContentBackground"},{"parameters":["class javax.swing.plaf.synth.SynthContext","class java.awt.Graphics","int","int","int","int","int"],"class":"javax.swing.plaf.synth.SynthPainter","function":"paintToolBarContentBackground"},{"parameters":["class javax.swing.plaf.synth.SynthContext","class java.awt.Graphics","int","int","int","int"],"class":"javax.swing.plaf.synth.SynthPainter","function":"paintToolBarContentBorder"},{"parameters":["class javax.swing.plaf.synth.SynthContext","class java.awt.Graphics","int","int","int","int","int"],"class":"javax.swing.plaf.synth.SynthPainter","function":"paintToolBarContentBorder"},{"parameters":["class javax.swing.plaf.synth.SynthContext","class java.awt.Graphics","int","int","int","int"],"class":"javax.swing.plaf.synth.SynthPainter","function":"paintToolBarDragWindowBackground"},{"parameters":["class javax.swing.plaf.synth.SynthContext","class java.awt.Graphics","int","int","int","int","int"],"class":"javax.swing.plaf.synth.SynthPainter","function":"paintToolBarDragWindowBackground"},{"parameters":["class javax.swing.plaf.synth.SynthContext","class java.awt.Graphics","int","int","int","int","int"],"class":"javax.swing.plaf.synth.SynthPainter","function":"paintToolBarDragWindowBorder"},{"parameters":["class javax.swing.plaf.synth.SynthContext","class java.awt.Graphics","int","int","int","int"],"class":"javax.swing.plaf.synth.SynthPainter","function":"paintToolBarDragWindowBorder"},{"parameters":["class javax.swing.plaf.synth.SynthContext","class java.awt.Graphics","int","int","int","int"],"class":"javax.swing.plaf.synth.SynthPainter","function":"paintToolTipBackground"},{"parameters":["class javax.swing.plaf.synth.SynthContext","class java.awt.Graphics","int","int","int","int"],"class":"javax.swing.plaf.synth.SynthPainter","function":"paintToolTipBorder"},{"parameters":["class javax.swing.plaf.synth.SynthContext","class java.awt.Graphics","int","int","int","int"],"class":"javax.swing.plaf.synth.SynthPainter","function":"paintTreeBackground"},{"parameters":["class javax.swing.plaf.synth.SynthContext","class java.awt.Graphics","int","int","int","int"],"class":"javax.swing.plaf.synth.SynthPainter","function":"paintTreeBorder"},{"parameters":["class javax.swing.plaf.synth.SynthContext","class java.awt.Graphics","int","int","int","int"],"class":"javax.swing.plaf.synth.SynthPainter","function":"paintTreeCellBackground"},{"parameters":["class javax.swing.plaf.synth.SynthContext","class java.awt.Graphics","int","int","int","int"],"class":"javax.swing.plaf.synth.SynthPainter","function":"paintTreeCellBorder"},{"parameters":["class javax.swing.plaf.synth.SynthContext","class java.awt.Graphics","int","int","int","int"],"class":"javax.swing.plaf.synth.SynthPainter","function":"paintTreeCellFocus"},{"parameters":["class javax.swing.plaf.synth.SynthContext","class java.awt.Graphics","int","int","int","int"],"class":"javax.swing.plaf.synth.SynthPainter","function":"paintViewportBackground"},{"parameters":["class javax.swing.plaf.synth.SynthContext","class java.awt.Graphics","int","int","int","int"],"class":"javax.swing.plaf.synth.SynthPainter","function":"paintViewportBorder"},{"parameters":["long"],"class":"javax.swing.plaf.synth.SynthPainter","function":"wait"},{"parameters":["long","int"],"class":"javax.swing.plaf.synth.SynthPainter","function":"wait"},{"parameters":[],"class":"javax.swing.plaf.synth.SynthPainter","function":"wait"},{"parameters":["class java.lang.Object"],"class":"javax.swing.plaf.synth.SynthPainter","function":"equals"},{"parameters":[],"class":"javax.swing.plaf.synth.SynthPainter","function":"toString"},{"parameters":[],"class":"javax.swing.plaf.synth.SynthPainter","function":"hashCode"},{"parameters":[],"class":"javax.swing.plaf.synth.SynthPainter","function":"getClass"},{"parameters":[],"class":"javax.swing.plaf.synth.SynthPainter","function":"notify"},{"parameters":[],"class":"javax.swing.plaf.synth.SynthPainter","function":"notifyAll"}]