[{"parameters":[],"class":"javax.sound.midi.MidiMessage","function":"getStatus"},{"parameters":[],"class":"javax.sound.midi.MidiMessage","function":"clone"},{"parameters":[],"class":"javax.sound.midi.MidiMessage","function":"getLength"},{"parameters":[],"class":"javax.sound.midi.MidiMessage","function":"getMessage"},{"parameters":["long"],"class":"javax.sound.midi.MidiMessage","function":"wait"},{"parameters":["long","int"],"class":"javax.sound.midi.MidiMessage","function":"wait"},{"parameters":[],"class":"javax.sound.midi.MidiMessage","function":"wait"},{"parameters":["class java.lang.Object"],"class":"javax.sound.midi.MidiMessage","function":"equals"},{"parameters":[],"class":"javax.sound.midi.MidiMessage","function":"toString"},{"parameters":[],"class":"javax.sound.midi.MidiMessage","function":"hashCode"},{"parameters":[],"class":"javax.sound.midi.MidiMessage","function":"getClass"},{"parameters":[],"class":"javax.sound.midi.MidiMessage","function":"notify"},{"parameters":[],"class":"javax.sound.midi.MidiMessage","function":"notifyAll"}]