[{"parameters":[],"class":"javax.lang.model.element.Parameterizable","function":"getTypeParameters"},{"parameters":[],"class":"javax.lang.model.element.Parameterizable","function":"getKind"},{"parameters":[],"class":"javax.lang.model.element.Parameterizable","function":"getEnclosingElement"},{"parameters":[],"class":"javax.lang.model.element.Parameterizable","function":"getEnclosedElements"},{"parameters":[],"class":"javax.lang.model.element.Parameterizable","function":"getAnnotationMirrors"},{"parameters":["class java.lang.Object"],"class":"javax.lang.model.element.Parameterizable","function":"equals"},{"parameters":[],"class":"javax.lang.model.element.Parameterizable","function":"hashCode"},{"parameters":[],"class":"javax.lang.model.element.Parameterizable","function":"getModifiers"},{"parameters":[],"class":"javax.lang.model.element.Parameterizable","function":"getSimpleName"},{"parameters":["java.lang.Class<A>"],"class":"javax.lang.model.element.Parameterizable","function":"getAnnotation"},{"parameters":["javax.lang.model.element.ElementVisitor<R, P>","P"],"class":"javax.lang.model.element.Parameterizable","function":"accept"},{"parameters":[],"class":"javax.lang.model.element.Parameterizable","function":"asType"},{"parameters":["java.lang.Class<A>"],"class":"javax.lang.model.element.Parameterizable","function":"getAnnotationsByType"}]