[{"parameters":[],"class":"java.util.IllformedLocaleException","function":"getErrorIndex"},{"parameters":["class java.io.PrintStream"],"class":"java.util.IllformedLocaleException","function":"printStackTrace"},{"parameters":[],"class":"java.util.IllformedLocaleException","function":"printStackTrace"},{"parameters":["class java.io.PrintWriter"],"class":"java.util.IllformedLocaleException","function":"printStackTrace"},{"parameters":[],"class":"java.util.IllformedLocaleException","function":"fillInStackTrace"},{"parameters":[],"class":"java.util.IllformedLocaleException","function":"getCause"},{"parameters":["class java.lang.Throwable"],"class":"java.util.IllformedLocaleException","function":"initCause"},{"parameters":[],"class":"java.util.IllformedLocaleException","function":"toString"},{"parameters":[],"class":"java.util.IllformedLocaleException","function":"getMessage"},{"parameters":[],"class":"java.util.IllformedLocaleException","function":"getSuppressed"},{"parameters":[],"class":"java.util.IllformedLocaleException","function":"getLocalizedMessage"},{"parameters":[],"class":"java.util.IllformedLocaleException","function":"getStackTrace"},{"parameters":["class [Ljava.lang.StackTraceElement;"],"class":"java.util.IllformedLocaleException","function":"setStackTrace"},{"parameters":["class java.lang.Throwable"],"class":"java.util.IllformedLocaleException","function":"addSuppressed"},{"parameters":["long"],"class":"java.util.IllformedLocaleException","function":"wait"},{"parameters":["long","int"],"class":"java.util.IllformedLocaleException","function":"wait"},{"parameters":[],"class":"java.util.IllformedLocaleException","function":"wait"},{"parameters":["class java.lang.Object"],"class":"java.util.IllformedLocaleException","function":"equals"},{"parameters":[],"class":"java.util.IllformedLocaleException","function":"hashCode"},{"parameters":[],"class":"java.util.IllformedLocaleException","function":"getClass"},{"parameters":[],"class":"java.util.IllformedLocaleException","function":"notify"},{"parameters":[],"class":"java.util.IllformedLocaleException","function":"notifyAll"}]