[{"parameters":[],"class":"javax.xml.crypto.URIReferenceException","function":"getURIReference"},{"parameters":["class java.io.PrintStream"],"class":"javax.xml.crypto.URIReferenceException","function":"printStackTrace"},{"parameters":["class java.io.PrintWriter"],"class":"javax.xml.crypto.URIReferenceException","function":"printStackTrace"},{"parameters":[],"class":"javax.xml.crypto.URIReferenceException","function":"printStackTrace"},{"parameters":[],"class":"javax.xml.crypto.URIReferenceException","function":"getCause"},{"parameters":[],"class":"javax.xml.crypto.URIReferenceException","function":"fillInStackTrace"},{"parameters":["class java.lang.Throwable"],"class":"javax.xml.crypto.URIReferenceException","function":"initCause"},{"parameters":[],"class":"javax.xml.crypto.URIReferenceException","function":"toString"},{"parameters":[],"class":"javax.xml.crypto.URIReferenceException","function":"getMessage"},{"parameters":[],"class":"javax.xml.crypto.URIReferenceException","function":"getSuppressed"},{"parameters":[],"class":"javax.xml.crypto.URIReferenceException","function":"getLocalizedMessage"},{"parameters":[],"class":"javax.xml.crypto.URIReferenceException","function":"getStackTrace"},{"parameters":["class [Ljava.lang.StackTraceElement;"],"class":"javax.xml.crypto.URIReferenceException","function":"setStackTrace"},{"parameters":["class java.lang.Throwable"],"class":"javax.xml.crypto.URIReferenceException","function":"addSuppressed"},{"parameters":["long"],"class":"javax.xml.crypto.URIReferenceException","function":"wait"},{"parameters":["long","int"],"class":"javax.xml.crypto.URIReferenceException","function":"wait"},{"parameters":[],"class":"javax.xml.crypto.URIReferenceException","function":"wait"},{"parameters":["class java.lang.Object"],"class":"javax.xml.crypto.URIReferenceException","function":"equals"},{"parameters":[],"class":"javax.xml.crypto.URIReferenceException","function":"hashCode"},{"parameters":[],"class":"javax.xml.crypto.URIReferenceException","function":"getClass"},{"parameters":[],"class":"javax.xml.crypto.URIReferenceException","function":"notify"},{"parameters":[],"class":"javax.xml.crypto.URIReferenceException","function":"notifyAll"}]