[{"parameters":["class java.time.format.TextStyle","class java.util.Locale"],"class":"java.time.Month","function":"getDisplayName"},{"parameters":["boolean"],"class":"java.time.Month","function":"firstDayOfYear"},{"parameters":[],"class":"java.time.Month","function":"maxLength"},{"parameters":["long"],"class":"java.time.Month","function":"minus"},{"parameters":["interface java.time.temporal.Temporal"],"class":"java.time.Month","function":"adjustInto"},{"parameters":[],"class":"java.time.Month","function":"firstMonthOfQuarter"},{"parameters":[],"class":"java.time.Month","function":"minLength"},{"parameters":["long"],"class":"java.time.Month","function":"plus"},{"parameters":["interface java.time.temporal.TemporalField"],"class":"java.time.Month","function":"range"},{"parameters":["interface java.time.temporal.TemporalField"],"class":"java.time.Month","function":"get"},{"parameters":["boolean"],"class":"java.time.Month","function":"length"},{"parameters":[],"class":"java.time.Month","function":"values"},{"parameters":["interface java.time.temporal.TemporalField"],"class":"java.time.Month","function":"getLong"},{"parameters":["class java.lang.String"],"class":"java.time.Month","function":"valueOf"},{"parameters":[],"class":"java.time.Month","function":"getValue"},{"parameters":["interface java.time.temporal.TemporalAccessor"],"class":"java.time.Month","function":"from"},{"parameters":["int"],"class":"java.time.Month","function":"of"},{"parameters":["java.time.temporal.TemporalQuery<R>"],"class":"java.time.Month","function":"query"},{"parameters":["interface java.time.temporal.TemporalField"],"class":"java.time.Month","function":"isSupported"},{"parameters":[],"class":"java.time.Month","function":"name"},{"parameters":["class java.lang.Object"],"class":"java.time.Month","function":"equals"},{"parameters":[],"class":"java.time.Month","function":"toString"},{"parameters":[],"class":"java.time.Month","function":"hashCode"},{"parameters":["class java.lang.Object"],"class":"java.time.Month","function":"compareTo"},{"parameters":["E"],"class":"java.time.Month","function":"compareTo"},{"parameters":["java.lang.Class<T>","class java.lang.String"],"class":"java.time.Month","function":"valueOf"},{"parameters":[],"class":"java.time.Month","function":"getDeclaringClass"},{"parameters":[],"class":"java.time.Month","function":"ordinal"},{"parameters":["long"],"class":"java.time.Month","function":"wait"},{"parameters":["long","int"],"class":"java.time.Month","function":"wait"},{"parameters":[],"class":"java.time.Month","function":"wait"},{"parameters":[],"class":"java.time.Month","function":"getClass"},{"parameters":[],"class":"java.time.Month","function":"notify"},{"parameters":[],"class":"java.time.Month","function":"notifyAll"}]