[{"parameters":["class java.lang.Object","class java.lang.Object"],"class":"javax.swing.text.Document","function":"putProperty"},{"parameters":["int","class java.lang.String","interface javax.swing.text.AttributeSet"],"class":"javax.swing.text.Document","function":"insertString"},{"parameters":["interface javax.swing.event.DocumentListener"],"class":"javax.swing.text.Document","function":"removeDocumentListener"},{"parameters":["interface javax.swing.event.DocumentListener"],"class":"javax.swing.text.Document","function":"addDocumentListener"},{"parameters":["int"],"class":"javax.swing.text.Document","function":"createPosition"},{"parameters":["interface javax.swing.event.UndoableEditListener"],"class":"javax.swing.text.Document","function":"addUndoableEditListener"},{"parameters":["interface javax.swing.event.UndoableEditListener"],"class":"javax.swing.text.Document","function":"removeUndoableEditListener"},{"parameters":[],"class":"javax.swing.text.Document","function":"getStartPosition"},{"parameters":[],"class":"javax.swing.text.Document","function":"getEndPosition"},{"parameters":[],"class":"javax.swing.text.Document","function":"getDefaultRootElement"},{"parameters":["interface java.lang.Runnable"],"class":"javax.swing.text.Document","function":"render"},{"parameters":["int","int","class javax.swing.text.Segment"],"class":"javax.swing.text.Document","function":"getText"},{"parameters":["int","int"],"class":"javax.swing.text.Document","function":"getText"},{"parameters":[],"class":"javax.swing.text.Document","function":"getRootElements"},{"parameters":["int","int"],"class":"javax.swing.text.Document","function":"remove"},{"parameters":["class java.lang.Object"],"class":"javax.swing.text.Document","function":"getProperty"},{"parameters":[],"class":"javax.swing.text.Document","function":"getLength"}]