[{"parameters":[],"class":"java.util.concurrent.atomic.AtomicBoolean","function":"get"},{"parameters":[],"class":"java.util.concurrent.atomic.AtomicBoolean","function":"toString"},{"parameters":["boolean"],"class":"java.util.concurrent.atomic.AtomicBoolean","function":"set"},{"parameters":[],"class":"java.util.concurrent.atomic.AtomicBoolean","function":"getOpaque"},{"parameters":["boolean"],"class":"java.util.concurrent.atomic.AtomicBoolean","function":"setOpaque"},{"parameters":[],"class":"java.util.concurrent.atomic.AtomicBoolean","function":"getAcquire"},{"parameters":["boolean"],"class":"java.util.concurrent.atomic.AtomicBoolean","function":"setRelease"},{"parameters":["boolean","boolean"],"class":"java.util.concurrent.atomic.AtomicBoolean","function":"compareAndSet"},{"parameters":["boolean","boolean"],"class":"java.util.concurrent.atomic.AtomicBoolean","function":"compareAndExchange"},{"parameters":["boolean","boolean"],"class":"java.util.concurrent.atomic.AtomicBoolean","function":"compareAndExchangeAcquire"},{"parameters":["boolean","boolean"],"class":"java.util.concurrent.atomic.AtomicBoolean","function":"compareAndExchangeRelease"},{"parameters":["boolean","boolean"],"class":"java.util.concurrent.atomic.AtomicBoolean","function":"weakCompareAndSetPlain"},{"parameters":["boolean","boolean"],"class":"java.util.concurrent.atomic.AtomicBoolean","function":"weakCompareAndSet"},{"parameters":["boolean","boolean"],"class":"java.util.concurrent.atomic.AtomicBoolean","function":"weakCompareAndSetAcquire"},{"parameters":["boolean","boolean"],"class":"java.util.concurrent.atomic.AtomicBoolean","function":"weakCompareAndSetRelease"},{"parameters":["boolean"],"class":"java.util.concurrent.atomic.AtomicBoolean","function":"getAndSet"},{"parameters":["boolean"],"class":"java.util.concurrent.atomic.AtomicBoolean","function":"lazySet"},{"parameters":[],"class":"java.util.concurrent.atomic.AtomicBoolean","function":"getPlain"},{"parameters":["boolean"],"class":"java.util.concurrent.atomic.AtomicBoolean","function":"setPlain"},{"parameters":["boolean","boolean"],"class":"java.util.concurrent.atomic.AtomicBoolean","function":"weakCompareAndSetVolatile"},{"parameters":["long"],"class":"java.util.concurrent.atomic.AtomicBoolean","function":"wait"},{"parameters":["long","int"],"class":"java.util.concurrent.atomic.AtomicBoolean","function":"wait"},{"parameters":[],"class":"java.util.concurrent.atomic.AtomicBoolean","function":"wait"},{"parameters":["class java.lang.Object"],"class":"java.util.concurrent.atomic.AtomicBoolean","function":"equals"},{"parameters":[],"class":"java.util.concurrent.atomic.AtomicBoolean","function":"hashCode"},{"parameters":[],"class":"java.util.concurrent.atomic.AtomicBoolean","function":"getClass"},{"parameters":[],"class":"java.util.concurrent.atomic.AtomicBoolean","function":"notify"},{"parameters":[],"class":"java.util.concurrent.atomic.AtomicBoolean","function":"notifyAll"}]