[{"parameters":[],"class":"javax.imageio.spi.ImageWriterSpi","function":"createWriterInstance"},{"parameters":["class java.lang.Object"],"class":"javax.imageio.spi.ImageWriterSpi","function":"createWriterInstance"},{"parameters":["class javax.imageio.ImageWriter"],"class":"javax.imageio.spi.ImageWriterSpi","function":"isOwnWriter"},{"parameters":[],"class":"javax.imageio.spi.ImageWriterSpi","function":"getImageReaderSpiNames"},{"parameters":[],"class":"javax.imageio.spi.ImageWriterSpi","function":"getOutputTypes"},{"parameters":[],"class":"javax.imageio.spi.ImageWriterSpi","function":"isFormatLossless"},{"parameters":["interface java.awt.image.RenderedImage"],"class":"javax.imageio.spi.ImageWriterSpi","function":"canEncodeImage"},{"parameters":["class javax.imageio.ImageTypeSpecifier"],"class":"javax.imageio.spi.ImageWriterSpi","function":"canEncodeImage"},{"parameters":[],"class":"javax.imageio.spi.ImageWriterSpi","function":"getPluginClassName"},{"parameters":[],"class":"javax.imageio.spi.ImageWriterSpi","function":"isStandardStreamMetadataFormatSupported"},{"parameters":[],"class":"javax.imageio.spi.ImageWriterSpi","function":"getNativeStreamMetadataFormatName"},{"parameters":[],"class":"javax.imageio.spi.ImageWriterSpi","function":"getExtraStreamMetadataFormatNames"},{"parameters":[],"class":"javax.imageio.spi.ImageWriterSpi","function":"isStandardImageMetadataFormatSupported"},{"parameters":[],"class":"javax.imageio.spi.ImageWriterSpi","function":"getNativeImageMetadataFormatName"},{"parameters":[],"class":"javax.imageio.spi.ImageWriterSpi","function":"getExtraImageMetadataFormatNames"},{"parameters":["class java.lang.String"],"class":"javax.imageio.spi.ImageWriterSpi","function":"getStreamMetadataFormat"},{"parameters":["class java.lang.String"],"class":"javax.imageio.spi.ImageWriterSpi","function":"getImageMetadataFormat"},{"parameters":[],"class":"javax.imageio.spi.ImageWriterSpi","function":"getFormatNames"},{"parameters":[],"class":"javax.imageio.spi.ImageWriterSpi","function":"getFileSuffixes"},{"parameters":[],"class":"javax.imageio.spi.ImageWriterSpi","function":"getMIMETypes"},{"parameters":["class javax.imageio.spi.ServiceRegistry","java.lang.Class<?>"],"class":"javax.imageio.spi.ImageWriterSpi","function":"onRegistration"},{"parameters":["class javax.imageio.spi.ServiceRegistry","java.lang.Class<?>"],"class":"javax.imageio.spi.ImageWriterSpi","function":"onDeregistration"},{"parameters":[],"class":"javax.imageio.spi.ImageWriterSpi","function":"getVendorName"},{"parameters":[],"class":"javax.imageio.spi.ImageWriterSpi","function":"getVersion"},{"parameters":["class java.util.Locale"],"class":"javax.imageio.spi.ImageWriterSpi","function":"getDescription"},{"parameters":["long"],"class":"javax.imageio.spi.ImageWriterSpi","function":"wait"},{"parameters":["long","int"],"class":"javax.imageio.spi.ImageWriterSpi","function":"wait"},{"parameters":[],"class":"javax.imageio.spi.ImageWriterSpi","function":"wait"},{"parameters":["class java.lang.Object"],"class":"javax.imageio.spi.ImageWriterSpi","function":"equals"},{"parameters":[],"class":"javax.imageio.spi.ImageWriterSpi","function":"toString"},{"parameters":[],"class":"javax.imageio.spi.ImageWriterSpi","function":"hashCode"},{"parameters":[],"class":"javax.imageio.spi.ImageWriterSpi","function":"getClass"},{"parameters":[],"class":"javax.imageio.spi.ImageWriterSpi","function":"notify"},{"parameters":[],"class":"javax.imageio.spi.ImageWriterSpi","function":"notifyAll"}]