[{"parameters":[],"class":"java.awt.Panel","function":"getAccessibleContext"},{"parameters":[],"class":"java.awt.Panel","function":"addNotify"},{"parameters":[],"class":"java.awt.Panel","function":"isValidateRoot"},{"parameters":[],"class":"java.awt.Panel","function":"layout"},{"parameters":["interface java.awt.LayoutManager"],"class":"java.awt.Panel","function":"setLayout"},{"parameters":[],"class":"java.awt.Panel","function":"getComponentCount"},{"parameters":[],"class":"java.awt.Panel","function":"countComponents"},{"parameters":["int"],"class":"java.awt.Panel","function":"getComponent"},{"parameters":[],"class":"java.awt.Panel","function":"getComponents"},{"parameters":[],"class":"java.awt.Panel","function":"getInsets"},{"parameters":[],"class":"java.awt.Panel","function":"insets"},{"parameters":["class java.awt.Component","int"],"class":"java.awt.Panel","function":"setComponentZOrder"},{"parameters":["class java.awt.Component"],"class":"java.awt.Panel","function":"getComponentZOrder"},{"parameters":[],"class":"java.awt.Panel","function":"getLayout"},{"parameters":[],"class":"java.awt.Panel","function":"doLayout"},{"parameters":["class java.awt.Font"],"class":"java.awt.Panel","function":"setFont"},{"parameters":[],"class":"java.awt.Panel","function":"getPreferredSize"},{"parameters":[],"class":"java.awt.Panel","function":"preferredSize"},{"parameters":[],"class":"java.awt.Panel","function":"getMinimumSize"},{"parameters":[],"class":"java.awt.Panel","function":"minimumSize"},{"parameters":[],"class":"java.awt.Panel","function":"getMaximumSize"},{"parameters":[],"class":"java.awt.Panel","function":"getAlignmentX"},{"parameters":[],"class":"java.awt.Panel","function":"getAlignmentY"},{"parameters":["class java.awt.Graphics"],"class":"java.awt.Panel","function":"paint"},{"parameters":["class java.awt.Graphics"],"class":"java.awt.Panel","function":"paintComponents"},{"parameters":["class java.awt.Graphics"],"class":"java.awt.Panel","function":"printComponents"},{"parameters":["interface java.awt.event.ContainerListener"],"class":"java.awt.Panel","function":"addContainerListener"},{"parameters":["interface java.awt.event.ContainerListener"],"class":"java.awt.Panel","function":"removeContainerListener"},{"parameters":[],"class":"java.awt.Panel","function":"getContainerListeners"},{"parameters":["java.lang.Class<T>"],"class":"java.awt.Panel","function":"getListeners"},{"parameters":["class java.awt.Event"],"class":"java.awt.Panel","function":"deliverEvent"},{"parameters":["int","int"],"class":"java.awt.Panel","function":"getComponentAt"},{"parameters":["class java.awt.Point"],"class":"java.awt.Panel","function":"getComponentAt"},{"parameters":["int","int"],"class":"java.awt.Panel","function":"locate"},{"parameters":["boolean"],"class":"java.awt.Panel","function":"getMousePosition"},{"parameters":["class java.awt.Point"],"class":"java.awt.Panel","function":"findComponentAt"},{"parameters":["int","int"],"class":"java.awt.Panel","function":"findComponentAt"},{"parameters":[],"class":"java.awt.Panel","function":"removeNotify"},{"parameters":["class java.awt.Component"],"class":"java.awt.Panel","function":"isAncestorOf"},{"parameters":["int","java.util.Set<? extends java.awt.AWTKeyStroke>"],"class":"java.awt.Panel","function":"setFocusTraversalKeys"},{"parameters":["int"],"class":"java.awt.Panel","function":"getFocusTraversalKeys"},{"parameters":["int"],"class":"java.awt.Panel","function":"areFocusTraversalKeysSet"},{"parameters":["class java.awt.Container"],"class":"java.awt.Panel","function":"isFocusCycleRoot"},{"parameters":[],"class":"java.awt.Panel","function":"isFocusCycleRoot"},{"parameters":["class java.awt.FocusTraversalPolicy"],"class":"java.awt.Panel","function":"setFocusTraversalPolicy"},{"parameters":[],"class":"java.awt.Panel","function":"getFocusTraversalPolicy"},{"parameters":[],"class":"java.awt.Panel","function":"isFocusTraversalPolicySet"},{"parameters":["boolean"],"class":"java.awt.Panel","function":"setFocusCycleRoot"},{"parameters":["boolean"],"class":"java.awt.Panel","function":"setFocusTraversalPolicyProvider"},{"parameters":[],"class":"java.awt.Panel","function":"isFocusTraversalPolicyProvider"},{"parameters":[],"class":"java.awt.Panel","function":"transferFocusDownCycle"},{"parameters":["class java.awt.ComponentOrientation"],"class":"java.awt.Panel","function":"applyComponentOrientation"},{"parameters":["interface java.beans.PropertyChangeListener"],"class":"java.awt.Panel","function":"addPropertyChangeListener"},{"parameters":["class java.lang.String","interface java.beans.PropertyChangeListener"],"class":"java.awt.Panel","function":"addPropertyChangeListener"},{"parameters":[],"class":"java.awt.Panel","function":"invalidate"},{"parameters":["class java.awt.Component","class java.lang.Object"],"class":"java.awt.Panel","function":"add"},{"parameters":["class java.lang.String","class java.awt.Component"],"class":"java.awt.Panel","function":"add"},{"parameters":["class java.awt.Component","class java.lang.Object","int"],"class":"java.awt.Panel","function":"add"},{"parameters":["class java.awt.Component"],"class":"java.awt.Panel","function":"add"},{"parameters":["class java.awt.Component","int"],"class":"java.awt.Panel","function":"add"},{"parameters":["class java.awt.Component"],"class":"java.awt.Panel","function":"remove"},{"parameters":["int"],"class":"java.awt.Panel","function":"remove"},{"parameters":["class java.awt.Graphics"],"class":"java.awt.Panel","function":"update"},{"parameters":["class java.io.PrintWriter","int"],"class":"java.awt.Panel","function":"list"},{"parameters":["class java.io.PrintStream","int"],"class":"java.awt.Panel","function":"list"},{"parameters":[],"class":"java.awt.Panel","function":"validate"},{"parameters":["class java.awt.Graphics"],"class":"java.awt.Panel","function":"print"},{"parameters":[],"class":"java.awt.Panel","function":"removeAll"},{"parameters":["class java.util.Locale"],"class":"java.awt.Panel","function":"setLocale"},{"parameters":["int","int"],"class":"java.awt.Panel","function":"createImage"},{"parameters":["interface java.awt.image.ImageProducer"],"class":"java.awt.Panel","function":"createImage"},{"parameters":[],"class":"java.awt.Panel","function":"getTreeLock"},{"parameters":[],"class":"java.awt.Panel","function":"getMousePosition"},{"parameters":[],"class":"java.awt.Panel","function":"isLightweight"},{"parameters":[],"class":"java.awt.Panel","function":"getGraphicsConfiguration"},{"parameters":["class java.awt.AWTEvent"],"class":"java.awt.Panel","function":"dispatchEvent"},{"parameters":[],"class":"java.awt.Panel","function":"isVisible"},{"parameters":[],"class":"java.awt.Panel","function":"isEnabled"},{"parameters":[],"class":"java.awt.Panel","function":"isDisplayable"},{"parameters":[],"class":"java.awt.Panel","function":"isFocusable"},{"parameters":[],"class":"java.awt.Panel","function":"isFocusOwner"},{"parameters":[],"class":"java.awt.Panel","function":"transferFocus"},{"parameters":[],"class":"java.awt.Panel","function":"getFont"},{"parameters":[],"class":"java.awt.Panel","function":"isPreferredSizeSet"},{"parameters":[],"class":"java.awt.Panel","function":"isMinimumSizeSet"},{"parameters":[],"class":"java.awt.Panel","function":"isMaximumSizeSet"},{"parameters":[],"class":"java.awt.Panel","function":"isShowing"},{"parameters":["class java.awt.Event"],"class":"java.awt.Panel","function":"handleEvent"},{"parameters":["class java.awt.Event"],"class":"java.awt.Panel","function":"postEvent"},{"parameters":[],"class":"java.awt.Panel","function":"transferFocusBackward"},{"parameters":[],"class":"java.awt.Panel","function":"getFocusCycleRootAncestor"},{"parameters":["class java.lang.String","char","char"],"class":"java.awt.Panel","function":"firePropertyChange"},{"parameters":["class java.lang.String","byte","byte"],"class":"java.awt.Panel","function":"firePropertyChange"},{"parameters":["class java.lang.String","long","long"],"class":"java.awt.Panel","function":"firePropertyChange"},{"parameters":["class java.lang.String","float","float"],"class":"java.awt.Panel","function":"firePropertyChange"},{"parameters":["class java.lang.String","double","double"],"class":"java.awt.Panel","function":"firePropertyChange"},{"parameters":["class java.lang.String","short","short"],"class":"java.awt.Panel","function":"firePropertyChange"},{"parameters":[],"class":"java.awt.Panel","function":"requestFocus"},{"parameters":["class java.awt.event.FocusEvent$Cause"],"class":"java.awt.Panel","function":"requestFocus"},{"parameters":["boolean"],"class":"java.awt.Panel","function":"setVisible"},{"parameters":["int","int","int","int"],"class":"java.awt.Panel","function":"setBounds"},{"parameters":["class java.awt.Rectangle"],"class":"java.awt.Panel","function":"setBounds"},{"parameters":["class java.awt.dnd.DropTarget"],"class":"java.awt.Panel","function":"setDropTarget"},{"parameters":[],"class":"java.awt.Panel","function":"getDropTarget"},{"parameters":[],"class":"java.awt.Panel","function":"getToolkit"},{"parameters":["boolean"],"class":"java.awt.Panel","function":"setEnabled"},{"parameters":[],"class":"java.awt.Panel","function":"isDoubleBuffered"},{"parameters":["boolean"],"class":"java.awt.Panel","function":"enableInputMethods"},{"parameters":["boolean"],"class":"java.awt.Panel","function":"show"},{"parameters":[],"class":"java.awt.Panel","function":"show"},{"parameters":[],"class":"java.awt.Panel","function":"hide"},{"parameters":[],"class":"java.awt.Panel","function":"getForeground"},{"parameters":["class java.awt.Color"],"class":"java.awt.Panel","function":"setForeground"},{"parameters":[],"class":"java.awt.Panel","function":"isForegroundSet"},{"parameters":[],"class":"java.awt.Panel","function":"getBackground"},{"parameters":["class java.awt.Color"],"class":"java.awt.Panel","function":"setBackground"},{"parameters":[],"class":"java.awt.Panel","function":"isBackgroundSet"},{"parameters":[],"class":"java.awt.Panel","function":"isFontSet"},{"parameters":[],"class":"java.awt.Panel","function":"getColorModel"},{"parameters":[],"class":"java.awt.Panel","function":"getLocationOnScreen"},{"parameters":["int","int","int","int"],"class":"java.awt.Panel","function":"reshape"},{"parameters":["class java.awt.Dimension"],"class":"java.awt.Panel","function":"setPreferredSize"},{"parameters":["class java.awt.Dimension"],"class":"java.awt.Panel","function":"setMinimumSize"},{"parameters":["class java.awt.Dimension"],"class":"java.awt.Panel","function":"setMaximumSize"},{"parameters":["int","int"],"class":"java.awt.Panel","function":"getBaseline"},{"parameters":[],"class":"java.awt.Panel","function":"getBaselineResizeBehavior"},{"parameters":[],"class":"java.awt.Panel","function":"revalidate"},{"parameters":["class java.awt.Font"],"class":"java.awt.Panel","function":"getFontMetrics"},{"parameters":["class java.awt.Cursor"],"class":"java.awt.Panel","function":"setCursor"},{"parameters":[],"class":"java.awt.Panel","function":"getCursor"},{"parameters":[],"class":"java.awt.Panel","function":"isCursorSet"},{"parameters":["class java.awt.Graphics"],"class":"java.awt.Panel","function":"paintAll"},{"parameters":[],"class":"java.awt.Panel","function":"repaint"},{"parameters":["long","int","int","int","int"],"class":"java.awt.Panel","function":"repaint"},{"parameters":["int","int","int","int"],"class":"java.awt.Panel","function":"repaint"},{"parameters":["long"],"class":"java.awt.Panel","function":"repaint"},{"parameters":["class java.awt.Graphics"],"class":"java.awt.Panel","function":"printAll"},{"parameters":["class java.awt.Image","int","int","int","int","int"],"class":"java.awt.Panel","function":"imageUpdate"},{"parameters":["int","int","class java.awt.ImageCapabilities"],"class":"java.awt.Panel","function":"createVolatileImage"},{"parameters":["int","int"],"class":"java.awt.Panel","function":"createVolatileImage"},{"parameters":["class java.awt.Image","interface java.awt.image.ImageObserver"],"class":"java.awt.Panel","function":"prepareImage"},{"parameters":["class java.awt.Image","int","int","interface java.awt.image.ImageObserver"],"class":"java.awt.Panel","function":"prepareImage"},{"parameters":["class java.awt.Image","int","int","interface java.awt.image.ImageObserver"],"class":"java.awt.Panel","function":"checkImage"},{"parameters":["class java.awt.Image","interface java.awt.image.ImageObserver"],"class":"java.awt.Panel","function":"checkImage"},{"parameters":["boolean"],"class":"java.awt.Panel","function":"setIgnoreRepaint"},{"parameters":[],"class":"java.awt.Panel","function":"getIgnoreRepaint"},{"parameters":["int","int"],"class":"java.awt.Panel","function":"inside"},{"parameters":["interface java.awt.event.ComponentListener"],"class":"java.awt.Panel","function":"addComponentListener"},{"parameters":["interface java.awt.event.ComponentListener"],"class":"java.awt.Panel","function":"removeComponentListener"},{"parameters":[],"class":"java.awt.Panel","function":"getComponentListeners"},{"parameters":["interface java.awt.event.FocusListener"],"class":"java.awt.Panel","function":"addFocusListener"},{"parameters":["interface java.awt.event.FocusListener"],"class":"java.awt.Panel","function":"removeFocusListener"},{"parameters":[],"class":"java.awt.Panel","function":"getFocusListeners"},{"parameters":["interface java.awt.event.HierarchyListener"],"class":"java.awt.Panel","function":"addHierarchyListener"},{"parameters":["interface java.awt.event.HierarchyListener"],"class":"java.awt.Panel","function":"removeHierarchyListener"},{"parameters":[],"class":"java.awt.Panel","function":"getHierarchyListeners"},{"parameters":["interface java.awt.event.HierarchyBoundsListener"],"class":"java.awt.Panel","function":"addHierarchyBoundsListener"},{"parameters":["interface java.awt.event.HierarchyBoundsListener"],"class":"java.awt.Panel","function":"removeHierarchyBoundsListener"},{"parameters":[],"class":"java.awt.Panel","function":"getHierarchyBoundsListeners"},{"parameters":["interface java.awt.event.KeyListener"],"class":"java.awt.Panel","function":"addKeyListener"},{"parameters":["interface java.awt.event.KeyListener"],"class":"java.awt.Panel","function":"removeKeyListener"},{"parameters":[],"class":"java.awt.Panel","function":"getKeyListeners"},{"parameters":["interface java.awt.event.MouseListener"],"class":"java.awt.Panel","function":"addMouseListener"},{"parameters":["interface java.awt.event.MouseListener"],"class":"java.awt.Panel","function":"removeMouseListener"},{"parameters":[],"class":"java.awt.Panel","function":"getMouseListeners"},{"parameters":["interface java.awt.event.MouseMotionListener"],"class":"java.awt.Panel","function":"addMouseMotionListener"},{"parameters":["interface java.awt.event.MouseMotionListener"],"class":"java.awt.Panel","function":"removeMouseMotionListener"},{"parameters":[],"class":"java.awt.Panel","function":"getMouseMotionListeners"},{"parameters":["interface java.awt.event.MouseWheelListener"],"class":"java.awt.Panel","function":"addMouseWheelListener"},{"parameters":["interface java.awt.event.MouseWheelListener"],"class":"java.awt.Panel","function":"removeMouseWheelListener"},{"parameters":[],"class":"java.awt.Panel","function":"getMouseWheelListeners"},{"parameters":["interface java.awt.event.InputMethodListener"],"class":"java.awt.Panel","function":"addInputMethodListener"},{"parameters":["interface java.awt.event.InputMethodListener"],"class":"java.awt.Panel","function":"removeInputMethodListener"},{"parameters":[],"class":"java.awt.Panel","function":"getInputMethodListeners"},{"parameters":[],"class":"java.awt.Panel","function":"getInputMethodRequests"},{"parameters":[],"class":"java.awt.Panel","function":"getInputContext"},{"parameters":["class java.awt.Event","int","int"],"class":"java.awt.Panel","function":"mouseDown"},{"parameters":["class java.awt.Event","int","int"],"class":"java.awt.Panel","function":"mouseDrag"},{"parameters":["class java.awt.Event","int","int"],"class":"java.awt.Panel","function":"mouseUp"},{"parameters":["class java.awt.Event","int","int"],"class":"java.awt.Panel","function":"mouseMove"},{"parameters":["class java.awt.Event","int","int"],"class":"java.awt.Panel","function":"mouseEnter"},{"parameters":["class java.awt.Event","int","int"],"class":"java.awt.Panel","function":"mouseExit"},{"parameters":["class java.awt.Event","int"],"class":"java.awt.Panel","function":"keyDown"},{"parameters":["class java.awt.Event","int"],"class":"java.awt.Panel","function":"keyUp"},{"parameters":["class java.awt.Event","class java.lang.Object"],"class":"java.awt.Panel","function":"gotFocus"},{"parameters":["class java.awt.Event","class java.lang.Object"],"class":"java.awt.Panel","function":"lostFocus"},{"parameters":[],"class":"java.awt.Panel","function":"isFocusTraversable"},{"parameters":["boolean"],"class":"java.awt.Panel","function":"setFocusable"},{"parameters":["boolean"],"class":"java.awt.Panel","function":"setFocusTraversalKeysEnabled"},{"parameters":[],"class":"java.awt.Panel","function":"getFocusTraversalKeysEnabled"},{"parameters":[],"class":"java.awt.Panel","function":"requestFocusInWindow"},{"parameters":["class java.awt.event.FocusEvent$Cause"],"class":"java.awt.Panel","function":"requestFocusInWindow"},{"parameters":[],"class":"java.awt.Panel","function":"nextFocus"},{"parameters":[],"class":"java.awt.Panel","function":"transferFocusUpCycle"},{"parameters":[],"class":"java.awt.Panel","function":"hasFocus"},{"parameters":["interface java.beans.PropertyChangeListener"],"class":"java.awt.Panel","function":"removePropertyChangeListener"},{"parameters":["class java.lang.String","interface java.beans.PropertyChangeListener"],"class":"java.awt.Panel","function":"removePropertyChangeListener"},{"parameters":[],"class":"java.awt.Panel","function":"getPropertyChangeListeners"},{"parameters":["class java.lang.String"],"class":"java.awt.Panel","function":"getPropertyChangeListeners"},{"parameters":["class java.awt.ComponentOrientation"],"class":"java.awt.Panel","function":"setComponentOrientation"},{"parameters":[],"class":"java.awt.Panel","function":"getComponentOrientation"},{"parameters":["int","int"],"class":"java.awt.Panel","function":"move"},{"parameters":[],"class":"java.awt.Panel","function":"getX"},{"parameters":[],"class":"java.awt.Panel","function":"getY"},{"parameters":[],"class":"java.awt.Panel","function":"disable"},{"parameters":[],"class":"java.awt.Panel","function":"getLocale"},{"parameters":[],"class":"java.awt.Panel","function":"getWidth"},{"parameters":["interface java.awt.Shape"],"class":"java.awt.Panel","function":"setMixingCutoutShape"},{"parameters":["class java.awt.Dimension"],"class":"java.awt.Panel","function":"setSize"},{"parameters":["int","int"],"class":"java.awt.Panel","function":"setSize"},{"parameters":[],"class":"java.awt.Panel","function":"getHeight"},{"parameters":[],"class":"java.awt.Panel","function":"getGraphics"},{"parameters":["boolean"],"class":"java.awt.Panel","function":"enable"},{"parameters":[],"class":"java.awt.Panel","function":"enable"},{"parameters":["class java.awt.Rectangle"],"class":"java.awt.Panel","function":"getBounds"},{"parameters":[],"class":"java.awt.Panel","function":"getBounds"},{"parameters":[],"class":"java.awt.Panel","function":"bounds"},{"parameters":[],"class":"java.awt.Panel","function":"isValid"},{"parameters":["int","int"],"class":"java.awt.Panel","function":"setLocation"},{"parameters":["class java.awt.Point"],"class":"java.awt.Panel","function":"setLocation"},{"parameters":["class java.awt.PopupMenu"],"class":"java.awt.Panel","function":"add"},{"parameters":["class java.awt.MenuComponent"],"class":"java.awt.Panel","function":"remove"},{"parameters":[],"class":"java.awt.Panel","function":"toString"},{"parameters":[],"class":"java.awt.Panel","function":"getName"},{"parameters":["class java.awt.Point"],"class":"java.awt.Panel","function":"contains"},{"parameters":["int","int"],"class":"java.awt.Panel","function":"contains"},{"parameters":["class java.io.PrintWriter"],"class":"java.awt.Panel","function":"list"},{"parameters":["class java.io.PrintStream"],"class":"java.awt.Panel","function":"list"},{"parameters":[],"class":"java.awt.Panel","function":"list"},{"parameters":[],"class":"java.awt.Panel","function":"size"},{"parameters":[],"class":"java.awt.Panel","function":"getParent"},{"parameters":["class java.awt.Point"],"class":"java.awt.Panel","function":"getLocation"},{"parameters":[],"class":"java.awt.Panel","function":"getLocation"},{"parameters":["class java.lang.String"],"class":"java.awt.Panel","function":"setName"},{"parameters":["class java.awt.Event","class java.lang.Object"],"class":"java.awt.Panel","function":"action"},{"parameters":[],"class":"java.awt.Panel","function":"location"},{"parameters":["class java.awt.Dimension"],"class":"java.awt.Panel","function":"getSize"},{"parameters":[],"class":"java.awt.Panel","function":"getSize"},{"parameters":[],"class":"java.awt.Panel","function":"isOpaque"},{"parameters":["int","int"],"class":"java.awt.Panel","function":"resize"},{"parameters":["class java.awt.Dimension"],"class":"java.awt.Panel","function":"resize"},{"parameters":["long"],"class":"java.awt.Panel","function":"wait"},{"parameters":["long","int"],"class":"java.awt.Panel","function":"wait"},{"parameters":[],"class":"java.awt.Panel","function":"wait"},{"parameters":["class java.lang.Object"],"class":"java.awt.Panel","function":"equals"},{"parameters":[],"class":"java.awt.Panel","function":"hashCode"},{"parameters":[],"class":"java.awt.Panel","function":"getClass"},{"parameters":[],"class":"java.awt.Panel","function":"notify"},{"parameters":[],"class":"java.awt.Panel","function":"notifyAll"}]