[{"parameters":["class java.security.Identity"],"class":"java.security.IdentityScope","function":"addIdentity"},{"parameters":[],"class":"java.security.IdentityScope","function":"getSystemScope"},{"parameters":["class java.lang.String"],"class":"java.security.IdentityScope","function":"getIdentity"},{"parameters":["interface java.security.Principal"],"class":"java.security.IdentityScope","function":"getIdentity"},{"parameters":["interface java.security.PublicKey"],"class":"java.security.IdentityScope","function":"getIdentity"},{"parameters":["class java.security.Identity"],"class":"java.security.IdentityScope","function":"removeIdentity"},{"parameters":[],"class":"java.security.IdentityScope","function":"identities"},{"parameters":[],"class":"java.security.IdentityScope","function":"toString"},{"parameters":[],"class":"java.security.IdentityScope","function":"size"},{"parameters":[],"class":"java.security.IdentityScope","function":"getInfo"},{"parameters":[],"class":"java.security.IdentityScope","function":"certificates"},{"parameters":["interface java.security.PublicKey"],"class":"java.security.IdentityScope","function":"setPublicKey"},{"parameters":["class java.lang.String"],"class":"java.security.IdentityScope","function":"setInfo"},{"parameters":["interface java.security.Certificate"],"class":"java.security.IdentityScope","function":"addCertificate"},{"parameters":["interface java.security.Certificate"],"class":"java.security.IdentityScope","function":"removeCertificate"},{"parameters":[],"class":"java.security.IdentityScope","function":"getScope"},{"parameters":["class java.lang.Object"],"class":"java.security.IdentityScope","function":"equals"},{"parameters":["boolean"],"class":"java.security.IdentityScope","function":"toString"},{"parameters":[],"class":"java.security.IdentityScope","function":"hashCode"},{"parameters":[],"class":"java.security.IdentityScope","function":"getName"},{"parameters":[],"class":"java.security.IdentityScope","function":"getPublicKey"},{"parameters":["long"],"class":"java.security.IdentityScope","function":"wait"},{"parameters":["long","int"],"class":"java.security.IdentityScope","function":"wait"},{"parameters":[],"class":"java.security.IdentityScope","function":"wait"},{"parameters":[],"class":"java.security.IdentityScope","function":"getClass"},{"parameters":[],"class":"java.security.IdentityScope","function":"notify"},{"parameters":[],"class":"java.security.IdentityScope","function":"notifyAll"},{"parameters":["class javax.security.auth.Subject"],"class":"java.security.IdentityScope","function":"implies"}]