[{"parameters":[],"class":"jdk.jfr.consumer.RecordedThread","function":"getOSName"},{"parameters":[],"class":"jdk.jfr.consumer.RecordedThread","function":"getOSThreadId"},{"parameters":[],"class":"jdk.jfr.consumer.RecordedThread","function":"getJavaName"},{"parameters":[],"class":"jdk.jfr.consumer.RecordedThread","function":"getJavaThreadId"},{"parameters":[],"class":"jdk.jfr.consumer.RecordedThread","function":"getThreadGroup"},{"parameters":[],"class":"jdk.jfr.consumer.RecordedThread","function":"getId"},{"parameters":["class java.lang.String"],"class":"jdk.jfr.consumer.RecordedThread","function":"getInstant"},{"parameters":["class java.lang.String"],"class":"jdk.jfr.consumer.RecordedThread","function":"getDuration"},{"parameters":["class java.lang.String"],"class":"jdk.jfr.consumer.RecordedThread","function":"getString"},{"parameters":["class java.lang.String"],"class":"jdk.jfr.consumer.RecordedThread","function":"hasField"},{"parameters":["class java.lang.String"],"class":"jdk.jfr.consumer.RecordedThread","function":"getThread"},{"parameters":[],"class":"jdk.jfr.consumer.RecordedThread","function":"toString"},{"parameters":["class java.lang.String"],"class":"jdk.jfr.consumer.RecordedThread","function":"getClass"},{"parameters":["class java.lang.String"],"class":"jdk.jfr.consumer.RecordedThread","function":"getBoolean"},{"parameters":["class java.lang.String"],"class":"jdk.jfr.consumer.RecordedThread","function":"getByte"},{"parameters":["class java.lang.String"],"class":"jdk.jfr.consumer.RecordedThread","function":"getShort"},{"parameters":["class java.lang.String"],"class":"jdk.jfr.consumer.RecordedThread","function":"getChar"},{"parameters":["class java.lang.String"],"class":"jdk.jfr.consumer.RecordedThread","function":"getInt"},{"parameters":["class java.lang.String"],"class":"jdk.jfr.consumer.RecordedThread","function":"getLong"},{"parameters":["class java.lang.String"],"class":"jdk.jfr.consumer.RecordedThread","function":"getFloat"},{"parameters":["class java.lang.String"],"class":"jdk.jfr.consumer.RecordedThread","function":"getDouble"},{"parameters":["class java.lang.String"],"class":"jdk.jfr.consumer.RecordedThread","function":"getValue"},{"parameters":[],"class":"jdk.jfr.consumer.RecordedThread","function":"getFields"},{"parameters":["long"],"class":"jdk.jfr.consumer.RecordedThread","function":"wait"},{"parameters":["long","int"],"class":"jdk.jfr.consumer.RecordedThread","function":"wait"},{"parameters":[],"class":"jdk.jfr.consumer.RecordedThread","function":"wait"},{"parameters":["class java.lang.Object"],"class":"jdk.jfr.consumer.RecordedThread","function":"equals"},{"parameters":[],"class":"jdk.jfr.consumer.RecordedThread","function":"hashCode"},{"parameters":[],"class":"jdk.jfr.consumer.RecordedThread","function":"getClass"},{"parameters":[],"class":"jdk.jfr.consumer.RecordedThread","function":"notify"},{"parameters":[],"class":"jdk.jfr.consumer.RecordedThread","function":"notifyAll"}]