[{"parameters":["class java.lang.String","class java.lang.Object"],"class":"jdk.nashorn.api.scripting.JSObject","function":"setMember"},{"parameters":["class java.lang.Object"],"class":"jdk.nashorn.api.scripting.JSObject","function":"isInstanceOf"},{"parameters":["class java.lang.Object","class [Ljava.lang.Object;"],"class":"jdk.nashorn.api.scripting.JSObject","function":"call"},{"parameters":["class java.lang.String"],"class":"jdk.nashorn.api.scripting.JSObject","function":"removeMember"},{"parameters":["class java.lang.String"],"class":"jdk.nashorn.api.scripting.JSObject","function":"eval"},{"parameters":["class java.lang.String"],"class":"jdk.nashorn.api.scripting.JSObject","function":"getMember"},{"parameters":["int","class java.lang.Object"],"class":"jdk.nashorn.api.scripting.JSObject","function":"setSlot"},{"parameters":["class [Ljava.lang.Object;"],"class":"jdk.nashorn.api.scripting.JSObject","function":"newObject"},{"parameters":["class java.lang.String"],"class":"jdk.nashorn.api.scripting.JSObject","function":"hasMember"},{"parameters":["int"],"class":"jdk.nashorn.api.scripting.JSObject","function":"hasSlot"},{"parameters":[],"class":"jdk.nashorn.api.scripting.JSObject","function":"isFunction"},{"parameters":[],"class":"jdk.nashorn.api.scripting.JSObject","function":"isStrictFunction"},{"parameters":[],"class":"jdk.nashorn.api.scripting.JSObject","function":"toNumber"},{"parameters":[],"class":"jdk.nashorn.api.scripting.JSObject","function":"values"},{"parameters":["class java.lang.Object"],"class":"jdk.nashorn.api.scripting.JSObject","function":"isInstance"},{"parameters":[],"class":"jdk.nashorn.api.scripting.JSObject","function":"isArray"},{"parameters":[],"class":"jdk.nashorn.api.scripting.JSObject","function":"keySet"},{"parameters":["java.lang.Class<?>"],"class":"jdk.nashorn.api.scripting.JSObject","function":"getDefaultValue"},{"parameters":["int"],"class":"jdk.nashorn.api.scripting.JSObject","function":"getSlot"},{"parameters":[],"class":"jdk.nashorn.api.scripting.JSObject","function":"getClassName"}]